{
  "ts": "2025-12-24T18:27:25.058Z",
  "frameId": 4640,
  "motionPercent": 65.36,
  "rois": [
    {
      "bbox": [
        268,
        412,
        335,
        447
      ]
    },
    {
      "bbox": [
        158,
        398,
        207,
        445
      ]
    },
    {
      "bbox": [
        372,
        129,
        430,
        221
      ]
    },
    {
      "bbox": [
        99,
        115,
        171,
        227
      ]
    },
    {
      "bbox": [
        4,
        11,
        59,
        63
      ]
    },
    {
      "bbox": [
        0,
        0,
        640,
        480
      ]
    },
    {
      "bbox": [
        313,
        0,
        357,
        22
      ]
    },
    {
      "bbox": [
        264,
        0,
        320,
        52
      ]
    },
    {
      "bbox": [
        0,
        0,
        269,
        170
      ]
    },
    {
      "bbox": [
        258,
        145,
        500,
        387
      ]
    }
  ]
}