{
  "ts": "2025-12-24T18:34:57.531Z",
  "frameId": 9205,
  "motionPercent": 56.4466,
  "rois": [
    {
      "bbox": [
        286,
        288,
        365,
        391
      ]
    },
    {
      "bbox": [
        287,
        229,
        360,
        279
      ]
    },
    {
      "bbox": [
        11,
        182,
        57,
        259
      ]
    },
    {
      "bbox": [
        109,
        137,
        143,
        185
      ]
    },
    {
      "bbox": [
        0,
        117,
        89,
        179
      ]
    },
    {
      "bbox": [
        0,
        47,
        27,
        107
      ]
    },
    {
      "bbox": [
        0,
        0,
        640,
        480
      ]
    },
    {
      "bbox": [
        54,
        0,
        117,
        77
      ]
    },
    {
      "bbox": [
        15,
        0,
        85,
        66
      ]
    },
    {
      "bbox": [
        239,
        221,
        437,
        419
      ]
    }
  ]
}