{
  "ts": "2026-01-27T21:42:05.922Z",
  "frameId": 7780,
  "motionPercent": 50.8252,
  "rois": [
    {
      "bbox": [
        305,
        428,
        334,
        462
      ]
    },
    {
      "bbox": [
        363,
        342,
        416,
        480
      ]
    },
    {
      "bbox": [
        118,
        312,
        173,
        359
      ]
    },
    {
      "bbox": [
        0,
        225,
        118,
        480
      ]
    },
    {
      "bbox": [
        171,
        0,
        640,
        480
      ]
    }
  ]
}