{
  "ts": "2026-05-04T19:25:57.944Z",
  "frameId": 675,
  "motionPercent": 24.8708,
  "rois": [
    {
      "bbox": [
        218,
        334,
        230,
        480
      ]
    },
    {
      "bbox": [
        577,
        247,
        636,
        319
      ]
    },
    {
      "bbox": [
        469,
        245,
        513,
        300
      ]
    },
    {
      "bbox": [
        44,
        242,
        74,
        289
      ]
    },
    {
      "bbox": [
        76,
        226,
        183,
        332
      ]
    },
    {
      "bbox": [
        387,
        193,
        432,
        256
      ]
    },
    {
      "bbox": [
        617,
        186,
        640,
        241
      ]
    },
    {
      "bbox": [
        471,
        174,
        499,
        229
      ]
    },
    {
      "bbox": [
        0,
        149,
        16,
        249
      ]
    },
    {
      "bbox": [
        271,
        146,
        507,
        480
      ]
    },
    {
      "bbox": [
        358,
        129,
        401,
        183
      ]
    },
    {
      "bbox": [
        74,
        107,
        93,
        155
      ]
    },
    {
      "bbox": [
        368,
        82,
        427,
        135
      ]
    },
    {
      "bbox": [
        58,
        65,
        93,
        103
      ]
    },
    {
      "bbox": [
        127,
        57,
        181,
        124
      ]
    },
    {
      "bbox": [
        339,
        29,
        427,
        87
      ]
    },
    {
      "bbox": [
        594,
        0,
        640,
        153
      ]
    },
    {
      "bbox": [
        441,
        0,
        532,
        178
      ]
    },
    {
      "bbox": [
        224,
        0,
        372,
        165
      ]
    },
    {
      "bbox": [
        0,
        0,
        78,
        81
      ]
    }
  ]
}