{
  "ts": "2026-01-27T21:32:25.912Z",
  "frameId": 3055,
  "motionPercent": 4.0029,
  "rois": [
    {
      "bbox": [
        228,
        413,
        294,
        480
      ]
    },
    {
      "bbox": [
        479,
        349,
        494,
        435
      ]
    },
    {
      "bbox": [
        413,
        302,
        453,
        359
      ]
    },
    {
      "bbox": [
        297,
        198,
        403,
        419
      ]
    },
    {
      "bbox": [
        366,
        249,
        528,
        411
      ]
    }
  ]
}