{
  "ts": "2025-12-24T18:40:29.886Z",
  "frameId": 12550,
  "motionPercent": 35.0589,
  "rois": [
    {
      "bbox": [
        228,
        423,
        257,
        460
      ]
    },
    {
      "bbox": [
        0,
        339,
        121,
        480
      ]
    },
    {
      "bbox": [
        110,
        291,
        327,
        480
      ]
    },
    {
      "bbox": [
        114,
        264,
        131,
        339
      ]
    },
    {
      "bbox": [
        396,
        80,
        432,
        480
      ]
    },
    {
      "bbox": [
        393,
        3,
        640,
        480
      ]
    }
  ]
}