{
  "ts": "2025-12-24T18:39:06.303Z",
  "frameId": 11660,
  "motionPercent": 2.8574,
  "rois": [
    {
      "bbox": [
        410,
        442,
        469,
        480
      ]
    },
    {
      "bbox": [
        255,
        397,
        284,
        437
      ]
    },
    {
      "bbox": [
        293,
        294,
        335,
        452
      ]
    },
    {
      "bbox": [
        202,
        287,
        291,
        417
      ]
    },
    {
      "bbox": [
        218,
        363,
        329,
        474
      ]
    }
  ]
}