{
  "ts": "2025-12-24T18:39:50.908Z",
  "frameId": 12135,
  "motionPercent": 71.4671,
  "rois": [
    {
      "bbox": [
        0,
        195,
        51,
        267
      ]
    },
    {
      "bbox": [
        31,
        142,
        85,
        202
      ]
    },
    {
      "bbox": [
        151,
        129,
        176,
        183
      ]
    },
    {
      "bbox": [
        78,
        64,
        132,
        103
      ]
    },
    {
      "bbox": [
        31,
        63,
        104,
        143
      ]
    },
    {
      "bbox": [
        0,
        0,
        640,
        480
      ]
    },
    {
      "bbox": [
        60,
        0,
        140,
        65
      ]
    },
    {
      "bbox": [
        0,
        0,
        47,
        175
      ]
    },
    {
      "bbox": [
        193,
        356,
        305,
        468
      ]
    }
  ]
}