{
  "ts": "2026-01-27T21:47:18.579Z",
  "frameId": 10685,
  "motionPercent": 67.8154,
  "rois": [
    {
      "bbox": [
        304,
        322,
        345,
        384
      ]
    },
    {
      "bbox": [
        47,
        273,
        81,
        311
      ]
    },
    {
      "bbox": [
        213,
        238,
        305,
        324
      ]
    },
    {
      "bbox": [
        284,
        214,
        348,
        287
      ]
    },
    {
      "bbox": [
        199,
        199,
        266,
        249
      ]
    },
    {
      "bbox": [
        141,
        176,
        213,
        239
      ]
    },
    {
      "bbox": [
        0,
        132,
        81,
        315
      ]
    },
    {
      "bbox": [
        0,
        58,
        274,
        480
      ]
    },
    {
      "bbox": [
        118,
        39,
        179,
        94
      ]
    },
    {
      "bbox": [
        154,
        0,
        640,
        480
      ]
    },
    {
      "bbox": [
        219,
        0,
        310,
        51
      ]
    },
    {
      "bbox": [
        188,
        0,
        220,
        39
      ]
    },
    {
      "bbox": [
        88,
        0,
        177,
        56
      ]
    },
    {
      "bbox": [
        0,
        0,
        90,
        131
      ]
    }
  ]
}