{
  "ts": "2026-01-27T21:34:20.528Z",
  "frameId": 4120,
  "motionPercent": 56.8389,
  "rois": [
    {
      "bbox": [
        122,
        311,
        169,
        369
      ]
    },
    {
      "bbox": [
        0,
        267,
        67,
        325
      ]
    },
    {
      "bbox": [
        300,
        253,
        371,
        339
      ]
    },
    {
      "bbox": [
        4,
        212,
        63,
        259
      ]
    },
    {
      "bbox": [
        76,
        198,
        113,
        289
      ]
    },
    {
      "bbox": [
        324,
        192,
        377,
        235
      ]
    },
    {
      "bbox": [
        312,
        154,
        364,
        199
      ]
    },
    {
      "bbox": [
        2,
        147,
        40,
        183
      ]
    },
    {
      "bbox": [
        56,
        137,
        131,
        188
      ]
    },
    {
      "bbox": [
        0,
        94,
        37,
        147
      ]
    },
    {
      "bbox": [
        26,
        68,
        85,
        167
      ]
    },
    {
      "bbox": [
        0,
        23,
        40,
        86
      ]
    },
    {
      "bbox": [
        0,
        0,
        640,
        480
      ]
    },
    {
      "bbox": [
        21,
        0,
        87,
        47
      ]
    },
    {
      "bbox": [
        453,
        21,
        518,
        86
      ]
    },
    {
      "bbox": [
        233,
        162,
        484,
        413
      ]
    }
  ]
}