{
  "ts": "2025-12-24T18:23:15.360Z",
  "frameId": 1945,
  "motionPercent": 58.7262,
  "rois": [
    {
      "bbox": [
        411,
        393,
        473,
        480
      ]
    },
    {
      "bbox": [
        12,
        282,
        51,
        323
      ]
    },
    {
      "bbox": [
        118,
        145,
        141,
        235
      ]
    },
    {
      "bbox": [
        0,
        0,
        640,
        480
      ]
    },
    {
      "bbox": [
        110,
        0,
        152,
        41
      ]
    },
    {
      "bbox": [
        210,
        115,
        406,
        311
      ]
    }
  ]
}