{
  "ts": "2026-01-11T17:22:48.101Z",
  "frameId": 410,
  "motionPercent": 3.9111,
  "rois": [
    {
      "bbox": [
        157,
        412,
        205,
        480
      ]
    },
    {
      "bbox": [
        286,
        399,
        309,
        442
      ]
    },
    {
      "bbox": [
        261,
        176,
        305,
        381
      ]
    },
    {
      "bbox": [
        437,
        138,
        461,
        377
      ]
    },
    {
      "bbox": [
        262,
        114,
        297,
        172
      ]
    }
  ]
}