{
  "ts": "2026-04-21T17:36:43.726Z",
  "frameId": 3840,
  "motionPercent": 30.8171,
  "rois": [
    {
      "bbox": [
        439,
        456,
        512,
        480
      ]
    },
    {
      "bbox": [
        0,
        452,
        43,
        469
      ]
    },
    {
      "bbox": [
        186,
        432,
        228,
        460
      ]
    },
    {
      "bbox": [
        198,
        392,
        228,
        428
      ]
    },
    {
      "bbox": [
        0,
        378,
        128,
        480
      ]
    },
    {
      "bbox": [
        200,
        333,
        247,
        369
      ]
    },
    {
      "bbox": [
        0,
        282,
        69,
        376
      ]
    },
    {
      "bbox": [
        201,
        201,
        245,
        299
      ]
    },
    {
      "bbox": [
        207,
        66,
        238,
        141
      ]
    },
    {
      "bbox": [
        0,
        62,
        153,
        287
      ]
    },
    {
      "bbox": [
        280,
        0,
        640,
        385
      ]
    },
    {
      "bbox": [
        0,
        0,
        71,
        38
      ]
    }
  ]
}