{
  "ts": "2026-01-27T21:34:03.167Z",
  "frameId": 3950,
  "motionPercent": 58.5234,
  "rois": [
    {
      "bbox": [
        289,
        258,
        373,
        358
      ]
    },
    {
      "bbox": [
        0,
        186,
        25,
        236
      ]
    },
    {
      "bbox": [
        0,
        184,
        73,
        254
      ]
    },
    {
      "bbox": [
        0,
        90,
        96,
        182
      ]
    },
    {
      "bbox": [
        0,
        21,
        79,
        97
      ]
    },
    {
      "bbox": [
        0,
        0,
        640,
        480
      ]
    },
    {
      "bbox": [
        222,
        169,
        473,
        420
      ]
    }
  ]
}