{
  "ts": "2026-01-27T21:33:09.527Z",
  "frameId": 3445,
  "motionPercent": 54.9215,
  "rois": [
    {
      "bbox": [
        299,
        275,
        362,
        357
      ]
    },
    {
      "bbox": [
        310,
        185,
        354,
        230
      ]
    },
    {
      "bbox": [
        16,
        150,
        77,
        221
      ]
    },
    {
      "bbox": [
        15,
        94,
        56,
        145
      ]
    },
    {
      "bbox": [
        120,
        83,
        159,
        131
      ]
    },
    {
      "bbox": [
        22,
        8,
        83,
        65
      ]
    },
    {
      "bbox": [
        0,
        0,
        640,
        480
      ]
    },
    {
      "bbox": [
        399,
        30,
        459,
        90
      ]
    },
    {
      "bbox": [
        225,
        194,
        459,
        428
      ]
    }
  ]
}