{
  "ts": "2025-12-24T18:34:20.705Z",
  "frameId": 8845,
  "motionPercent": 56.7331,
  "rois": [
    {
      "bbox": [
        148,
        363,
        206,
        403
      ]
    },
    {
      "bbox": [
        289,
        355,
        329,
        389
      ]
    },
    {
      "bbox": [
        258,
        287,
        339,
        384
      ]
    },
    {
      "bbox": [
        280,
        230,
        319,
        284
      ]
    },
    {
      "bbox": [
        58,
        208,
        138,
        318
      ]
    },
    {
      "bbox": [
        0,
        180,
        77,
        241
      ]
    },
    {
      "bbox": [
        0,
        140,
        24,
        191
      ]
    },
    {
      "bbox": [
        0,
        0,
        640,
        480
      ]
    },
    {
      "bbox": [
        0,
        0,
        114,
        91
      ]
    },
    {
      "bbox": [
        211,
        216,
        417,
        422
      ]
    }
  ]
}