{
  "ts": "2025-12-24T18:42:17.567Z",
  "frameId": 13665,
  "motionPercent": 56.5479,
  "rois": [
    {
      "bbox": [
        277,
        285,
        351,
        391
      ]
    },
    {
      "bbox": [
        64,
        260,
        93,
        320
      ]
    },
    {
      "bbox": [
        282,
        230,
        356,
        267
      ]
    },
    {
      "bbox": [
        42,
        199,
        88,
        236
      ]
    },
    {
      "bbox": [
        129,
        152,
        176,
        208
      ]
    },
    {
      "bbox": [
        0,
        132,
        84,
        304
      ]
    },
    {
      "bbox": [
        46,
        104,
        93,
        151
      ]
    },
    {
      "bbox": [
        0,
        95,
        32,
        132
      ]
    },
    {
      "bbox": [
        179,
        6,
        225,
        39
      ]
    },
    {
      "bbox": [
        0,
        0,
        640,
        480
      ]
    },
    {
      "bbox": [
        45,
        0,
        98,
        48
      ]
    },
    {
      "bbox": [
        0,
        0,
        67,
        76
      ]
    },
    {
      "bbox": [
        220,
        214,
        442,
        436
      ]
    }
  ]
}