{
  "ts": "2026-01-27T21:36:37.121Z",
  "frameId": 5215,
  "motionPercent": 38.9447,
  "rois": [
    {
      "bbox": [
        0,
        362,
        96,
        480
      ]
    },
    {
      "bbox": [
        295,
        258,
        392,
        382
      ]
    },
    {
      "bbox": [
        283,
        215,
        332,
        262
      ]
    },
    {
      "bbox": [
        317,
        157,
        369,
        186
      ]
    },
    {
      "bbox": [
        104,
        0,
        640,
        480
      ]
    },
    {
      "bbox": [
        243,
        170,
        495,
        422
      ]
    }
  ]
}