{
  "ts": "2026-05-04T19:33:10.293Z",
  "frameId": 4895,
  "motionPercent": 33.3167,
  "rois": [
    {
      "bbox": [
        582,
        446,
        616,
        480
      ]
    },
    {
      "bbox": [
        0,
        426,
        40,
        480
      ]
    },
    {
      "bbox": [
        582,
        218,
        640,
        442
      ]
    },
    {
      "bbox": [
        177,
        101,
        249,
        160
      ]
    },
    {
      "bbox": [
        0,
        0,
        640,
        480
      ]
    },
    {
      "bbox": [
        42,
        0,
        179,
        41
      ]
    }
  ]
}