{
  "ts": "2026-04-21T17:34:32.571Z",
  "frameId": 2350,
  "motionPercent": 45.3854,
  "rois": [
    {
      "bbox": [
        143,
        223,
        179,
        309
      ]
    },
    {
      "bbox": [
        603,
        166,
        632,
        216
      ]
    },
    {
      "bbox": [
        29,
        132,
        86,
        374
      ]
    },
    {
      "bbox": [
        56,
        100,
        151,
        462
      ]
    },
    {
      "bbox": [
        0,
        91,
        24,
        183
      ]
    },
    {
      "bbox": [
        0,
        46,
        28,
        90
      ]
    },
    {
      "bbox": [
        123,
        29,
        153,
        139
      ]
    },
    {
      "bbox": [
        136,
        0,
        640,
        480
      ]
    },
    {
      "bbox": [
        358,
        0,
        434,
        125
      ]
    },
    {
      "bbox": [
        142,
        0,
        171,
        52
      ]
    },
    {
      "bbox": [
        1,
        0,
        59,
        48
      ]
    }
  ]
}