{
  "ts": "2026-05-04T19:34:20.003Z",
  "frameId": 5615,
  "motionPercent": 27.9398,
  "rois": [
    {
      "bbox": [
        0,
        438,
        27,
        480
      ]
    },
    {
      "bbox": [
        250,
        364,
        387,
        480
      ]
    },
    {
      "bbox": [
        429,
        345,
        640,
        480
      ]
    },
    {
      "bbox": [
        343,
        283,
        457,
        405
      ]
    },
    {
      "bbox": [
        318,
        254,
        347,
        363
      ]
    },
    {
      "bbox": [
        338,
        192,
        485,
        285
      ]
    },
    {
      "bbox": [
        42,
        22,
        227,
        121
      ]
    },
    {
      "bbox": [
        194,
        0,
        606,
        244
      ]
    },
    {
      "bbox": [
        302,
        204,
        534,
        436
      ]
    }
  ]
}