{
  "ts": "2026-05-04T19:28:39.934Z",
  "frameId": 2265,
  "motionPercent": 37.6878,
  "rois": [
    {
      "bbox": [
        330,
        414,
        364,
        480
      ]
    },
    {
      "bbox": [
        270,
        280,
        336,
        383
      ]
    },
    {
      "bbox": [
        323,
        160,
        369,
        251
      ]
    },
    {
      "bbox": [
        262,
        131,
        288,
        168
      ]
    },
    {
      "bbox": [
        315,
        114,
        353,
        141
      ]
    },
    {
      "bbox": [
        8,
        90,
        49,
        143
      ]
    },
    {
      "bbox": [
        348,
        88,
        382,
        129
      ]
    },
    {
      "bbox": [
        75,
        82,
        264,
        262
      ]
    },
    {
      "bbox": [
        206,
        0,
        640,
        480
      ]
    },
    {
      "bbox": [
        73,
        0,
        169,
        46
      ]
    },
    {
      "bbox": [
        0,
        0,
        109,
        69
      ]
    }
  ]
}