{
  "ts": "2026-04-21T17:33:58.047Z",
  "frameId": 2005,
  "motionPercent": 39.0326,
  "rois": [
    {
      "bbox": [
        391,
        429,
        455,
        466
      ]
    },
    {
      "bbox": [
        99,
        421,
        155,
        480
      ]
    },
    {
      "bbox": [
        586,
        413,
        620,
        477
      ]
    },
    {
      "bbox": [
        63,
        356,
        86,
        480
      ]
    },
    {
      "bbox": [
        107,
        341,
        171,
        403
      ]
    },
    {
      "bbox": [
        419,
        294,
        473,
        330
      ]
    },
    {
      "bbox": [
        304,
        243,
        448,
        480
      ]
    },
    {
      "bbox": [
        110,
        241,
        163,
        354
      ]
    },
    {
      "bbox": [
        557,
        199,
        603,
        317
      ]
    },
    {
      "bbox": [
        122,
        150,
        188,
        233
      ]
    },
    {
      "bbox": [
        386,
        129,
        440,
        147
      ]
    },
    {
      "bbox": [
        139,
        59,
        179,
        84
      ]
    },
    {
      "bbox": [
        164,
        0,
        640,
        480
      ]
    },
    {
      "bbox": [
        0,
        0,
        81,
        480
      ]
    }
  ]
}