{
  "ts": "2026-01-27T21:33:40.099Z",
  "frameId": 3725,
  "motionPercent": 54.9518,
  "rois": [
    {
      "bbox": [
        306,
        279,
        373,
        356
      ]
    },
    {
      "bbox": [
        344,
        218,
        381,
        251
      ]
    },
    {
      "bbox": [
        0,
        190,
        135,
        480
      ]
    },
    {
      "bbox": [
        310,
        187,
        357,
        209
      ]
    },
    {
      "bbox": [
        19,
        170,
        80,
        210
      ]
    },
    {
      "bbox": [
        93,
        126,
        133,
        199
      ]
    },
    {
      "bbox": [
        20,
        65,
        117,
        130
      ]
    },
    {
      "bbox": [
        28,
        35,
        68,
        81
      ]
    },
    {
      "bbox": [
        4,
        6,
        75,
        46
      ]
    },
    {
      "bbox": [
        106,
        0,
        640,
        480
      ]
    },
    {
      "bbox": [
        114,
        0,
        159,
        20
      ]
    },
    {
      "bbox": [
        239,
        202,
        454,
        417
      ]
    }
  ]
}