{
  "ts": "2026-05-04T19:29:16.194Z",
  "frameId": 2625,
  "motionPercent": 22.7041,
  "rois": [
    {
      "bbox": [
        172,
        438,
        234,
        480
      ]
    },
    {
      "bbox": [
        241,
        430,
        283,
        480
      ]
    },
    {
      "bbox": [
        381,
        189,
        421,
        231
      ]
    },
    {
      "bbox": [
        557,
        183,
        599,
        317
      ]
    },
    {
      "bbox": [
        355,
        150,
        403,
        205
      ]
    },
    {
      "bbox": [
        328,
        135,
        359,
        213
      ]
    },
    {
      "bbox": [
        393,
        121,
        439,
        186
      ]
    },
    {
      "bbox": [
        467,
        0,
        559,
        450
      ]
    },
    {
      "bbox": [
        0,
        0,
        214,
        452
      ]
    }
  ]
}