{
  "ts": "2026-01-27T21:39:57.642Z",
  "frameId": 6660,
  "motionPercent": 52.514,
  "rois": [
    {
      "bbox": [
        0,
        336,
        109,
        480
      ]
    },
    {
      "bbox": [
        327,
        287,
        405,
        369
      ]
    },
    {
      "bbox": [
        85,
        279,
        105,
        335
      ]
    },
    {
      "bbox": [
        95,
        221,
        115,
        283
      ]
    },
    {
      "bbox": [
        74,
        137,
        118,
        220
      ]
    },
    {
      "bbox": [
        60,
        32,
        114,
        87
      ]
    },
    {
      "bbox": [
        6,
        29,
        46,
        86
      ]
    },
    {
      "bbox": [
        114,
        0,
        640,
        480
      ]
    },
    {
      "bbox": [
        263,
        206,
        498,
        441
      ]
    }
  ]
}