{
  "ts": "2025-12-24T18:22:57.808Z",
  "frameId": 1770,
  "motionPercent": 14.9076,
  "rois": [
    {
      "bbox": [
        93,
        348,
        301,
        480
      ]
    },
    {
      "bbox": [
        44,
        330,
        141,
        422
      ]
    },
    {
      "bbox": [
        273,
        194,
        318,
        250
      ]
    },
    {
      "bbox": [
        143,
        25,
        410,
        343
      ]
    },
    {
      "bbox": [
        204,
        119,
        413,
        328
      ]
    }
  ]
}