{
  "ts": "2026-05-04T19:29:47.362Z",
  "frameId": 2930,
  "motionPercent": 35.2461,
  "rois": [
    {
      "bbox": [
        358,
        389,
        403,
        436
      ]
    },
    {
      "bbox": [
        149,
        345,
        187,
        384
      ]
    },
    {
      "bbox": [
        162,
        271,
        201,
        355
      ]
    },
    {
      "bbox": [
        378,
        217,
        423,
        266
      ]
    },
    {
      "bbox": [
        451,
        182,
        481,
        225
      ]
    },
    {
      "bbox": [
        229,
        177,
        450,
        428
      ]
    },
    {
      "bbox": [
        0,
        132,
        55,
        214
      ]
    },
    {
      "bbox": [
        437,
        0,
        640,
        480
      ]
    },
    {
      "bbox": [
        0,
        0,
        267,
        480
      ]
    },
    {
      "bbox": [
        0,
        0,
        91,
        112
      ]
    }
  ]
}