{
  "ts": "2026-01-27T21:46:46.316Z",
  "frameId": 10385,
  "motionPercent": 48.2119,
  "rois": [
    {
      "bbox": [
        391,
        435,
        436,
        480
      ]
    },
    {
      "bbox": [
        491,
        360,
        530,
        421
      ]
    },
    {
      "bbox": [
        109,
        358,
        325,
        480
      ]
    },
    {
      "bbox": [
        0,
        349,
        103,
        480
      ]
    },
    {
      "bbox": [
        75,
        293,
        112,
        361
      ]
    },
    {
      "bbox": [
        373,
        0,
        640,
        449
      ]
    }
  ]
}