{
  "ts": "2026-01-27T21:42:34.065Z",
  "frameId": 8040,
  "motionPercent": 74.2611,
  "rois": [
    {
      "bbox": [
        172,
        191,
        212,
        233
      ]
    },
    {
      "bbox": [
        287,
        163,
        360,
        241
      ]
    },
    {
      "bbox": [
        3,
        163,
        89,
        256
      ]
    },
    {
      "bbox": [
        134,
        132,
        167,
        179
      ]
    },
    {
      "bbox": [
        0,
        120,
        69,
        162
      ]
    },
    {
      "bbox": [
        284,
        61,
        339,
        102
      ]
    },
    {
      "bbox": [
        0,
        0,
        640,
        480
      ]
    }
  ]
}