{
  "ts": "2026-01-11T18:59:39.524Z",
  "frameId": 1365,
  "motionPercent": 59.9824,
  "rois": [
    {
      "bbox": [
        293,
        457,
        358,
        480
      ]
    },
    {
      "bbox": [
        382,
        446,
        446,
        480
      ]
    },
    {
      "bbox": [
        447,
        441,
        500,
        480
      ]
    },
    {
      "bbox": [
        269,
        406,
        380,
        466
      ]
    },
    {
      "bbox": [
        200,
        133,
        280,
        205
      ]
    },
    {
      "bbox": [
        468,
        7,
        640,
        80
      ]
    },
    {
      "bbox": [
        0,
        0,
        640,
        480
      ]
    }
  ]
}