{
  "ts": "2025-12-24T18:20:53.073Z",
  "frameId": 525,
  "motionPercent": 30.9014,
  "rois": [
    {
      "bbox": [
        268,
        231,
        387,
        356
      ]
    },
    {
      "bbox": [
        270,
        182,
        371,
        227
      ]
    },
    {
      "bbox": [
        295,
        150,
        373,
        181
      ]
    },
    {
      "bbox": [
        375,
        147,
        437,
        376
      ]
    },
    {
      "bbox": [
        0,
        70,
        423,
        480
      ]
    },
    {
      "bbox": [
        402,
        0,
        640,
        443
      ]
    },
    {
      "bbox": [
        230,
        167,
        431,
        368
      ]
    }
  ]
}