{
  "ts": "2026-05-04T19:26:44.088Z",
  "frameId": 1130,
  "motionPercent": 29.3021,
  "rois": [
    {
      "bbox": [
        366,
        412,
        425,
        427
      ]
    },
    {
      "bbox": [
        591,
        409,
        640,
        465
      ]
    },
    {
      "bbox": [
        590,
        349,
        639,
        417
      ]
    },
    {
      "bbox": [
        152,
        313,
        197,
        414
      ]
    },
    {
      "bbox": [
        239,
        270,
        366,
        390
      ]
    },
    {
      "bbox": [
        79,
        262,
        170,
        295
      ]
    },
    {
      "bbox": [
        153,
        251,
        205,
        295
      ]
    },
    {
      "bbox": [
        368,
        247,
        411,
        288
      ]
    },
    {
      "bbox": [
        180,
        226,
        262,
        290
      ]
    },
    {
      "bbox": [
        2,
        217,
        135,
        480
      ]
    },
    {
      "bbox": [
        588,
        196,
        640,
        233
      ]
    },
    {
      "bbox": [
        569,
        107,
        634,
        185
      ]
    },
    {
      "bbox": [
        557,
        0,
        638,
        96
      ]
    },
    {
      "bbox": [
        418,
        0,
        581,
        480
      ]
    },
    {
      "bbox": [
        213,
        0,
        275,
        48
      ]
    },
    {
      "bbox": [
        0,
        0,
        47,
        204
      ]
    }
  ]
}