{
  "ts": "2026-04-21T17:34:33.055Z",
  "frameId": 2355,
  "motionPercent": 46.3255,
  "rois": [
    {
      "bbox": [
        604,
        296,
        640,
        349
      ]
    },
    {
      "bbox": [
        592,
        234,
        640,
        262
      ]
    },
    {
      "bbox": [
        570,
        65,
        640,
        219
      ]
    },
    {
      "bbox": [
        0,
        49,
        55,
        245
      ]
    },
    {
      "bbox": [
        132,
        0,
        640,
        480
      ]
    },
    {
      "bbox": [
        6,
        0,
        179,
        452
      ]
    },
    {
      "bbox": [
        17,
        0,
        64,
        34
      ]
    },
    {
      "bbox": [
        0,
        0,
        42,
        83
      ]
    }
  ]
}