{
  "ts": "2025-12-24T18:22:23.489Z",
  "frameId": 1430,
  "motionPercent": 68.6833,
  "rois": [
    {
      "bbox": [
        490,
        435,
        578,
        480
      ]
    },
    {
      "bbox": [
        467,
        434,
        507,
        469
      ]
    },
    {
      "bbox": [
        426,
        434,
        472,
        480
      ]
    },
    {
      "bbox": [
        176,
        403,
        231,
        447
      ]
    },
    {
      "bbox": [
        245,
        367,
        317,
        473
      ]
    },
    {
      "bbox": [
        79,
        76,
        187,
        223
      ]
    },
    {
      "bbox": [
        0,
        74,
        96,
        171
      ]
    },
    {
      "bbox": [
        0,
        0,
        640,
        480
      ]
    },
    {
      "bbox": [
        196,
        0,
        250,
        48
      ]
    },
    {
      "bbox": [
        13,
        0,
        195,
        106
      ]
    },
    {
      "bbox": [
        229,
        110,
        441,
        322
      ]
    }
  ]
}