{
  "ts": "2026-01-27T21:43:43.258Z",
  "frameId": 8685,
  "motionPercent": 74.151,
  "rois": [
    {
      "bbox": [
        294,
        414,
        351,
        462
      ]
    },
    {
      "bbox": [
        298,
        354,
        360,
        398
      ]
    },
    {
      "bbox": [
        45,
        198,
        77,
        236
      ]
    },
    {
      "bbox": [
        0,
        197,
        28,
        246
      ]
    },
    {
      "bbox": [
        15,
        158,
        83,
        223
      ]
    },
    {
      "bbox": [
        0,
        134,
        39,
        187
      ]
    },
    {
      "bbox": [
        0,
        0,
        640,
        480
      ]
    }
  ]
}