{
  "ts": "2026-05-04T19:33:44.718Z",
  "frameId": 5235,
  "motionPercent": 24.2786,
  "rois": [
    {
      "bbox": [
        0,
        443,
        39,
        480
      ]
    },
    {
      "bbox": [
        538,
        434,
        570,
        480
      ]
    },
    {
      "bbox": [
        207,
        430,
        233,
        480
      ]
    },
    {
      "bbox": [
        244,
        421,
        304,
        480
      ]
    },
    {
      "bbox": [
        217,
        390,
        254,
        441
      ]
    },
    {
      "bbox": [
        0,
        382,
        61,
        453
      ]
    },
    {
      "bbox": [
        0,
        349,
        37,
        384
      ]
    },
    {
      "bbox": [
        69,
        339,
        135,
        381
      ]
    },
    {
      "bbox": [
        21,
        278,
        132,
        346
      ]
    },
    {
      "bbox": [
        548,
        227,
        640,
        480
      ]
    },
    {
      "bbox": [
        315,
        212,
        496,
        476
      ]
    },
    {
      "bbox": [
        586,
        156,
        640,
        201
      ]
    },
    {
      "bbox": [
        196,
        48,
        269,
        102
      ]
    },
    {
      "bbox": [
        425,
        0,
        640,
        208
      ]
    }
  ]
}