{
  "ts": "2026-01-27T21:28:35.024Z",
  "frameId": 890,
  "motionPercent": 63.2415,
  "rois": [
    {
      "bbox": [
        308,
        420,
        371,
        457
      ]
    },
    {
      "bbox": [
        341,
        375,
        373,
        421
      ]
    },
    {
      "bbox": [
        158,
        259,
        206,
        314
      ]
    },
    {
      "bbox": [
        329,
        235,
        395,
        280
      ]
    },
    {
      "bbox": [
        68,
        225,
        114,
        297
      ]
    },
    {
      "bbox": [
        317,
        196,
        411,
        240
      ]
    },
    {
      "bbox": [
        130,
        86,
        193,
        268
      ]
    },
    {
      "bbox": [
        0,
        0,
        640,
        480
      ]
    },
    {
      "bbox": [
        130,
        0,
        205,
        54
      ]
    },
    {
      "bbox": [
        0,
        0,
        137,
        210
      ]
    },
    {
      "bbox": [
        0,
        0,
        61,
        43
      ]
    },
    {
      "bbox": [
        476,
        17,
        544,
        85
      ]
    },
    {
      "bbox": [
        246,
        222,
        480,
        456
      ]
    }
  ]
}