{
  "ts": "2026-01-27T21:31:31.261Z",
  "frameId": 2535,
  "motionPercent": 53.7699,
  "rois": [
    {
      "bbox": [
        112,
        430,
        145,
        469
      ]
    },
    {
      "bbox": [
        298,
        292,
        368,
        367
      ]
    },
    {
      "bbox": [
        0,
        238,
        133,
        480
      ]
    },
    {
      "bbox": [
        302,
        200,
        365,
        227
      ]
    },
    {
      "bbox": [
        18,
        142,
        61,
        185
      ]
    },
    {
      "bbox": [
        60,
        80,
        113,
        122
      ]
    },
    {
      "bbox": [
        127,
        0,
        640,
        480
      ]
    },
    {
      "bbox": [
        109,
        0,
        162,
        32
      ]
    },
    {
      "bbox": [
        236,
        216,
        455,
        435
      ]
    }
  ]
}