{
  "ts": "2025-12-24T18:36:26.882Z",
  "frameId": 10095,
  "motionPercent": 57.0078,
  "rois": [
    {
      "bbox": [
        259,
        244,
        294,
        279
      ]
    },
    {
      "bbox": [
        290,
        240,
        347,
        279
      ]
    },
    {
      "bbox": [
        102,
        189,
        163,
        317
      ]
    },
    {
      "bbox": [
        0,
        174,
        68,
        269
      ]
    },
    {
      "bbox": [
        57,
        112,
        124,
        161
      ]
    },
    {
      "bbox": [
        0,
        51,
        46,
        173
      ]
    },
    {
      "bbox": [
        0,
        0,
        640,
        480
      ]
    },
    {
      "bbox": [
        18,
        0,
        86,
        58
      ]
    },
    {
      "bbox": [
        225,
        215,
        429,
        419
      ]
    }
  ]
}