{
  "ts": "2026-01-27T21:45:15.042Z",
  "frameId": 9540,
  "motionPercent": 68.6185,
  "rois": [
    {
      "bbox": [
        231,
        320,
        307,
        391
      ]
    },
    {
      "bbox": [
        438,
        289,
        485,
        327
      ]
    },
    {
      "bbox": [
        134,
        245,
        241,
        308
      ]
    },
    {
      "bbox": [
        239,
        240,
        381,
        333
      ]
    },
    {
      "bbox": [
        321,
        207,
        367,
        244
      ]
    },
    {
      "bbox": [
        187,
        182,
        303,
        245
      ]
    },
    {
      "bbox": [
        300,
        180,
        352,
        211
      ]
    },
    {
      "bbox": [
        121,
        179,
        204,
        249
      ]
    },
    {
      "bbox": [
        118,
        150,
        155,
        203
      ]
    },
    {
      "bbox": [
        306,
        26,
        358,
        99
      ]
    },
    {
      "bbox": [
        0,
        0,
        640,
        480
      ]
    },
    {
      "bbox": [
        198,
        0,
        257,
        60
      ]
    },
    {
      "bbox": [
        64,
        0,
        165,
        160
      ]
    },
    {
      "bbox": [
        19,
        0,
        73,
        25
      ]
    }
  ]
}