{
  "ts": "2026-01-27T21:36:57.116Z",
  "frameId": 5380,
  "motionPercent": 5.4502,
  "rois": [
    {
      "bbox": [
        105,
        398,
        193,
        480
      ]
    },
    {
      "bbox": [
        369,
        257,
        396,
        309
      ]
    },
    {
      "bbox": [
        432,
        99,
        477,
        253
      ]
    },
    {
      "bbox": [
        250,
        80,
        393,
        388
      ]
    },
    {
      "bbox": [
        238,
        167,
        488,
        417
      ]
    }
  ]
}