{
  "ts": "2026-05-04T19:33:14.436Z",
  "frameId": 4935,
  "motionPercent": 23.6855,
  "rois": [
    {
      "bbox": [
        322,
        400,
        393,
        471
      ]
    },
    {
      "bbox": [
        21,
        388,
        89,
        465
      ]
    },
    {
      "bbox": [
        0,
        378,
        42,
        421
      ]
    },
    {
      "bbox": [
        327,
        358,
        382,
        393
      ]
    },
    {
      "bbox": [
        422,
        332,
        640,
        480
      ]
    },
    {
      "bbox": [
        334,
        271,
        380,
        332
      ]
    },
    {
      "bbox": [
        586,
        270,
        638,
        303
      ]
    },
    {
      "bbox": [
        262,
        237,
        315,
        289
      ]
    },
    {
      "bbox": [
        424,
        224,
        471,
        276
      ]
    },
    {
      "bbox": [
        583,
        223,
        631,
        276
      ]
    },
    {
      "bbox": [
        353,
        200,
        409,
        229
      ]
    },
    {
      "bbox": [
        84,
        135,
        262,
        480
      ]
    },
    {
      "bbox": [
        585,
        115,
        640,
        222
      ]
    },
    {
      "bbox": [
        305,
        90,
        342,
        135
      ]
    },
    {
      "bbox": [
        197,
        39,
        309,
        129
      ]
    },
    {
      "bbox": [
        296,
        10,
        586,
        152
      ]
    },
    {
      "bbox": [
        361,
        108,
        572,
        319
      ]
    }
  ]
}