{
  "ts": "2026-05-04T19:27:03.394Z",
  "frameId": 1320,
  "motionPercent": 31.3219,
  "rois": [
    {
      "bbox": [
        352,
        447,
        389,
        480
      ]
    },
    {
      "bbox": [
        245,
        412,
        289,
        445
      ]
    },
    {
      "bbox": [
        85,
        390,
        142,
        412
      ]
    },
    {
      "bbox": [
        337,
        365,
        410,
        466
      ]
    },
    {
      "bbox": [
        511,
        336,
        537,
        456
      ]
    },
    {
      "bbox": [
        108,
        298,
        135,
        343
      ]
    },
    {
      "bbox": [
        341,
        250,
        375,
        278
      ]
    },
    {
      "bbox": [
        537,
        192,
        609,
        480
      ]
    },
    {
      "bbox": [
        339,
        0,
        581,
        188
      ]
    },
    {
      "bbox": [
        0,
        0,
        336,
        480
      ]
    },
    {
      "bbox": [
        0,
        0,
        63,
        37
      ]
    }
  ]
}