{
  "ts": "2026-01-27T21:30:59.255Z",
  "frameId": 2205,
  "motionPercent": 55.1051,
  "rois": [
    {
      "bbox": [
        0,
        338,
        136,
        480
      ]
    },
    {
      "bbox": [
        275,
        278,
        362,
        371
      ]
    },
    {
      "bbox": [
        325,
        210,
        392,
        261
      ]
    },
    {
      "bbox": [
        302,
        184,
        348,
        213
      ]
    },
    {
      "bbox": [
        87,
        177,
        126,
        349
      ]
    },
    {
      "bbox": [
        43,
        71,
        97,
        111
      ]
    },
    {
      "bbox": [
        116,
        58,
        141,
        117
      ]
    },
    {
      "bbox": [
        97,
        0,
        640,
        480
      ]
    },
    {
      "bbox": [
        74,
        0,
        123,
        56
      ]
    },
    {
      "bbox": [
        393,
        31,
        452,
        90
      ]
    },
    {
      "bbox": [
        227,
        202,
        442,
        417
      ]
    }
  ]
}