{
  "ts": "2026-01-27T21:27:40.219Z",
  "frameId": 430,
  "motionPercent": 63.6634,
  "rois": [
    {
      "bbox": [
        262,
        398,
        307,
        443
      ]
    },
    {
      "bbox": [
        189,
        344,
        221,
        405
      ]
    },
    {
      "bbox": [
        307,
        308,
        374,
        403
      ]
    },
    {
      "bbox": [
        278,
        302,
        308,
        357
      ]
    },
    {
      "bbox": [
        275,
        265,
        327,
        291
      ]
    },
    {
      "bbox": [
        292,
        185,
        348,
        264
      ]
    },
    {
      "bbox": [
        0,
        140,
        34,
        207
      ]
    },
    {
      "bbox": [
        26,
        137,
        96,
        187
      ]
    },
    {
      "bbox": [
        98,
        87,
        172,
        281
      ]
    },
    {
      "bbox": [
        0,
        0,
        640,
        480
      ]
    },
    {
      "bbox": [
        315,
        0,
        359,
        51
      ]
    },
    {
      "bbox": [
        0,
        0,
        187,
        131
      ]
    },
    {
      "bbox": [
        478,
        18,
        544,
        84
      ]
    },
    {
      "bbox": [
        223,
        210,
        474,
        461
      ]
    }
  ]
}