{
  "ts": "2026-05-04T19:25:37.684Z",
  "frameId": 460,
  "motionPercent": 36.9671,
  "rois": [
    {
      "bbox": [
        0,
        429,
        57,
        480
      ]
    },
    {
      "bbox": [
        58,
        414,
        91,
        447
      ]
    },
    {
      "bbox": [
        503,
        377,
        640,
        480
      ]
    },
    {
      "bbox": [
        428,
        351,
        504,
        480
      ]
    },
    {
      "bbox": [
        326,
        342,
        395,
        450
      ]
    },
    {
      "bbox": [
        336,
        303,
        404,
        334
      ]
    },
    {
      "bbox": [
        269,
        230,
        458,
        480
      ]
    },
    {
      "bbox": [
        0,
        201,
        64,
        427
      ]
    },
    {
      "bbox": [
        339,
        157,
        436,
        231
      ]
    },
    {
      "bbox": [
        65,
        97,
        95,
        163
      ]
    },
    {
      "bbox": [
        186,
        63,
        275,
        480
      ]
    },
    {
      "bbox": [
        349,
        57,
        419,
        139
      ]
    },
    {
      "bbox": [
        288,
        36,
        344,
        223
      ]
    },
    {
      "bbox": [
        87,
        25,
        118,
        92
      ]
    },
    {
      "bbox": [
        319,
        5,
        386,
        54
      ]
    },
    {
      "bbox": [
        237,
        0,
        322,
        65
      ]
    },
    {
      "bbox": [
        80,
        0,
        210,
        480
      ]
    },
    {
      "bbox": [
        394,
        64,
        626,
        296
      ]
    }
  ]
}