{
  "ts": "2025-12-24T18:27:15.841Z",
  "frameId": 4540,
  "motionPercent": 66.0283,
  "rois": [
    {
      "bbox": [
        355,
        447,
        413,
        480
      ]
    },
    {
      "bbox": [
        193,
        433,
        226,
        480
      ]
    },
    {
      "bbox": [
        326,
        348,
        362,
        388
      ]
    },
    {
      "bbox": [
        154,
        161,
        209,
        193
      ]
    },
    {
      "bbox": [
        33,
        106,
        68,
        165
      ]
    },
    {
      "bbox": [
        185,
        19,
        254,
        87
      ]
    },
    {
      "bbox": [
        0,
        0,
        640,
        480
      ]
    },
    {
      "bbox": [
        297,
        0,
        347,
        45
      ]
    },
    {
      "bbox": [
        0,
        0,
        293,
        177
      ]
    },
    {
      "bbox": [
        254,
        143,
        504,
        393
      ]
    }
  ]
}