{
  "ts": "2026-05-04T19:30:56.604Z",
  "frameId": 3605,
  "motionPercent": 30.6507,
  "rois": [
    {
      "bbox": [
        319,
        421,
        357,
        448
      ]
    },
    {
      "bbox": [
        102,
        382,
        139,
        410
      ]
    },
    {
      "bbox": [
        0,
        354,
        77,
        412
      ]
    },
    {
      "bbox": [
        333,
        230,
        387,
        286
      ]
    },
    {
      "bbox": [
        68,
        204,
        117,
        274
      ]
    },
    {
      "bbox": [
        119,
        202,
        195,
        281
      ]
    },
    {
      "bbox": [
        377,
        193,
        427,
        272
      ]
    },
    {
      "bbox": [
        192,
        185,
        389,
        432
      ]
    },
    {
      "bbox": [
        492,
        180,
        534,
        211
      ]
    },
    {
      "bbox": [
        535,
        168,
        572,
        223
      ]
    },
    {
      "bbox": [
        614,
        17,
        640,
        93
      ]
    },
    {
      "bbox": [
        388,
        0,
        615,
        480
      ]
    },
    {
      "bbox": [
        206,
        0,
        271,
        11
      ]
    },
    {
      "bbox": [
        0,
        0,
        96,
        355
      ]
    }
  ]
}