{
  "ts": "2026-01-27T21:40:26.159Z",
  "frameId": 6895,
  "motionPercent": 40.1745,
  "rois": [
    {
      "bbox": [
        161,
        450,
        203,
        480
      ]
    },
    {
      "bbox": [
        0,
        366,
        85,
        480
      ]
    },
    {
      "bbox": [
        213,
        328,
        265,
        400
      ]
    },
    {
      "bbox": [
        221,
        221,
        272,
        249
      ]
    },
    {
      "bbox": [
        80,
        0,
        640,
        480
      ]
    },
    {
      "bbox": [
        139,
        251,
        352,
        464
      ]
    }
  ]
}