{
  "ts": "2026-01-27T21:40:44.902Z",
  "frameId": 7060,
  "motionPercent": 57.1898,
  "rois": [
    {
      "bbox": [
        34,
        290,
        75,
        327
      ]
    },
    {
      "bbox": [
        0,
        159,
        33,
        215
      ]
    },
    {
      "bbox": [
        79,
        151,
        119,
        237
      ]
    },
    {
      "bbox": [
        9,
        108,
        50,
        149
      ]
    },
    {
      "bbox": [
        26,
        78,
        73,
        130
      ]
    },
    {
      "bbox": [
        116,
        64,
        151,
        123
      ]
    },
    {
      "bbox": [
        0,
        0,
        640,
        480
      ]
    },
    {
      "bbox": [
        8,
        0,
        106,
        72
      ]
    }
  ]
}