{
  "ts": "2026-05-04T19:31:37.885Z",
  "frameId": 3995,
  "motionPercent": 27.1341,
  "rois": [
    {
      "bbox": [
        198,
        440,
        292,
        480
      ]
    },
    {
      "bbox": [
        299,
        381,
        343,
        416
      ]
    },
    {
      "bbox": [
        330,
        337,
        435,
        480
      ]
    },
    {
      "bbox": [
        18,
        322,
        46,
        366
      ]
    },
    {
      "bbox": [
        84,
        293,
        148,
        333
      ]
    },
    {
      "bbox": [
        208,
        286,
        300,
        429
      ]
    },
    {
      "bbox": [
        262,
        277,
        310,
        324
      ]
    },
    {
      "bbox": [
        462,
        224,
        490,
        261
      ]
    },
    {
      "bbox": [
        142,
        224,
        317,
        362
      ]
    },
    {
      "bbox": [
        0,
        216,
        128,
        309
      ]
    },
    {
      "bbox": [
        454,
        158,
        499,
        215
      ]
    },
    {
      "bbox": [
        534,
        0,
        640,
        480
      ]
    },
    {
      "bbox": [
        306,
        0,
        512,
        372
      ]
    },
    {
      "bbox": [
        141,
        0,
        204,
        30
      ]
    },
    {
      "bbox": [
        445,
        8,
        503,
        66
      ]
    }
  ]
}