{
  "ts": "2025-12-24T18:36:48.428Z",
  "frameId": 10305,
  "motionPercent": 57.1009,
  "rois": [
    {
      "bbox": [
        287,
        283,
        351,
        384
      ]
    },
    {
      "bbox": [
        289,
        242,
        339,
        276
      ]
    },
    {
      "bbox": [
        22,
        200,
        75,
        241
      ]
    },
    {
      "bbox": [
        102,
        190,
        147,
        333
      ]
    },
    {
      "bbox": [
        0,
        151,
        40,
        196
      ]
    },
    {
      "bbox": [
        34,
        116,
        73,
        150
      ]
    },
    {
      "bbox": [
        0,
        93,
        39,
        141
      ]
    },
    {
      "bbox": [
        24,
        66,
        104,
        159
      ]
    },
    {
      "bbox": [
        0,
        46,
        25,
        96
      ]
    },
    {
      "bbox": [
        13,
        22,
        65,
        70
      ]
    },
    {
      "bbox": [
        0,
        0,
        640,
        480
      ]
    },
    {
      "bbox": [
        11,
        0,
        111,
        51
      ]
    },
    {
      "bbox": [
        227,
        215,
        434,
        422
      ]
    }
  ]
}