{
  "ts": "2025-12-24T18:33:52.702Z",
  "frameId": 8560,
  "motionPercent": 56.834,
  "rois": [
    {
      "bbox": [
        0,
        347,
        29,
        404
      ]
    },
    {
      "bbox": [
        258,
        236,
        322,
        298
      ]
    },
    {
      "bbox": [
        104,
        190,
        141,
        341
      ]
    },
    {
      "bbox": [
        153,
        162,
        186,
        199
      ]
    },
    {
      "bbox": [
        0,
        152,
        53,
        209
      ]
    },
    {
      "bbox": [
        116,
        131,
        147,
        187
      ]
    },
    {
      "bbox": [
        0,
        62,
        47,
        141
      ]
    },
    {
      "bbox": [
        0,
        0,
        640,
        480
      ]
    },
    {
      "bbox": [
        230,
        211,
        428,
        409
      ]
    }
  ]
}