{
  "ts": "2026-01-27T21:37:55.856Z",
  "frameId": 5840,
  "motionPercent": 42.2018,
  "rois": [
    {
      "bbox": [
        0,
        364,
        85,
        480
      ]
    },
    {
      "bbox": [
        66,
        361,
        97,
        423
      ]
    },
    {
      "bbox": [
        312,
        302,
        370,
        377
      ]
    },
    {
      "bbox": [
        92,
        0,
        640,
        480
      ]
    },
    {
      "bbox": [
        230,
        221,
        456,
        447
      ]
    }
  ]
}